.DS_Store
seeq/.DS_Store
seeq/addons/.DS_Store
seeq/addons/plot_digitizer/__init__.py
seeq/addons/plot_digitizer/__main__.py
seeq/addons/plot_digitizer/_copy.py
seeq/addons/plot_digitizer/_html.py
seeq/addons/plot_digitizer/_interpolators.py
seeq/addons/plot_digitizer/_permissions.py
seeq/addons/plot_digitizer/_seeq_utils.py
seeq/addons/plot_digitizer/_utils.py
seeq/addons/plot_digitizer/_version.py
seeq/addons/plot_digitizer/deployment_notebook/plot_digitizer_master.ipynb
seeq_plot_digitizer-0.1.4.dist-info/LICENSE
seeq_plot_digitizer-0.1.4.dist-info/METADATA
seeq_plot_digitizer-0.1.4.dist-info/WHEEL
seeq_plot_digitizer-0.1.4.dist-info/top_level.txt
seeq_plot_digitizer-0.1.4.dist-info/RECORD
