Metadata-Version: 2.1
Name: seeq-plot-digitizer
Version: 0.1.4
Summary: Plot digitization in Seeq
Home-page: https://github.com/eparsonnet93/seeq-plot-digitizer
Author: Eric Parsonnet
Author-email: e.parsonnet@berkeley.edu
License: Apache License 2.0
Platform: Linux
Platform: Windows
Classifier: Programming Language :: Python :: 3.7
Classifier: License :: OSI Approved :: Apache Software License
Classifier: Operating System :: OS Independent
Requires-Python: >=3.7
License-File: LICENSE
Requires-Dist: bokeh (>=2.4.2)
Requires-Dist: imageio (>=2.19.3)
Requires-Dist: numpy (>=1.22.0)
Requires-Dist: pandas (>=1.3.3)
